XMind-1.2.0.dist-info/METADATA
XMind-1.2.0.dist-info/RECORD
XMind-1.2.0.dist-info/WHEEL
XMind-1.2.0.dist-info/top_level.txt
xmind/__about__.py
xmind/__init__.py
xmind/utils.py
xmind/core/__init__.py
xmind/core/comments.py
xmind/core/const.py
xmind/core/labels.py
xmind/core/loader.py
xmind/core/markerref.py
xmind/core/mixin.py
xmind/core/notes.py
xmind/core/position.py
xmind/core/relationship.py
xmind/core/saver.py
xmind/core/sheet.py
xmind/core/styles.py
xmind/core/title.py
xmind/core/topic.py
xmind/core/workbook.py
