Metadata-Version: 2.1
Name: XMind
Version: 1.2.0
Summary: XMind是基于Python实现，提供了对XMind思维导图进行创建、解析、更新的一站式解决方案！
Home-page: https://github.com/zhuifengshen/xmind
Author: Devin
Author-email: 1324556701@qq.com
License: MIT
Keywords: xmind, mind mapping, 思维导图, XMind思维导图
Platform: UNKNOWN
Classifier: Programming Language :: Python :: 3
Classifier: License :: OSI Approved :: MIT License
Classifier: Operating System :: OS Independent
Requires-Python: >=3.0, <4
